slam/__init__.py
slam/analysis.py
slam/apogee.py
slam/binning.py
slam/config.py
slam/costfunction.py
slam/diagnostic.py
slam/hyperparameter.py
slam/lndi.py
slam/logger.py
slam/mcmc.py
slam/model.py
slam/normalization.py
slam/parallel.py
slam/plotting.py
slam/postprocessing.py
slam/predict.py
slam/slam.py
slam/slam2.py
slam/slam3.py
slam/standardization.py
slam/train.py
slam/train2.py
slam/utils.py
slam/data/OpticalLineList.csv
slam/extern/__init__.py
slam/extern/interpolate.py
slam/extern/polynomial.py
astroslam-1.2022.1228.1.dist-info/LICENSE
astroslam-1.2022.1228.1.dist-info/METADATA
astroslam-1.2022.1228.1.dist-info/WHEEL
astroslam-1.2022.1228.1.dist-info/top_level.txt
astroslam-1.2022.1228.1.dist-info/RECORD
