Metadata-Version: 2.1
Name: astroslam
Version: 1.2022.1228.1
Summary: A forward model using SVR to estimate stellar parameters from spectra.
Home-page: http://github.com/hypergravity/astroslam
Author: Bo Zhang
Author-email: bozhang@nao.cas.cn
License: MIT
Classifier: Development Status :: 5 - Production/Stable
Classifier: Intended Audience :: Science/Research
Classifier: License :: OSI Approved :: MIT License
Classifier: Operating System :: OS Independent
Classifier: Programming Language :: Python :: 3.9
Classifier: Topic :: Scientific/Engineering :: Physics
Classifier: Topic :: Scientific/Engineering :: Astronomy
License-File: LICENSE
Requires-Dist: numpy
Requires-Dist: scipy
Requires-Dist: matplotlib
Requires-Dist: astropy
Requires-Dist: laspec
Requires-Dist: scikit-learn (==1.2.0)
Requires-Dist: joblib (==1.2.0)
Requires-Dist: pandas
Requires-Dist: emcee
Requires-Dist: lmfit
Requires-Dist: ipyparallel
